[

     


    {"name": "AAA", "topicName": "AAA"},  
     
    
    {"name": "BBB", "topicName": "BBB"},


    {"name": "Christianity", "topicName": "Christianity"},


    {"name": "Death", "topicName": "Death"},
    {"name": "Dogs", "topicName": "Dogs"},    

    {"name": "EEE", "topicName": "EEE"},


    {"name": "FFF", "topicName": "FFF"},


    {"name": "Golf", "topicName": "Golf"},
    {"name": "Greed", "topicName": "Greed"},
    {"name": "Groups", "topicName": "Groups"},    

    {"name": "Happiness", "topicName": "Happiness"},


    {"name": "III", "topicName": "III"},


    {"name": "JJJ", "topicName": "JJJ"},


    {"name": "KKKK", "topicName": "KKKK"},


    {"name": "LLL", "topicName": "LLL"},


    {"name": "Management 101", "topicName": "Management101"},
    {"name": "Men & Women", "topicName": "MenAndWomen"},


    {"name": "NNN", "topicName": "NNN"},


    {"name": "Old age", "topicName": "OldAge"},


    {"name": "Personnel Development", "topicName": "PersonnelDevelopment"},   
    {"name": "Posterity", "topicName": "Posterity"},
    {"name": "Power", "topicName": "Power"},

    {"name": "QQQ", "topicName": "QQQ"},


    {"name": "Religion", "topicName": "Religion"},


    {"name": "Sacrifice", "topicName": "Sacrifice"},


    {"name": "TTT", "topicName": "TTT"},


    {"name": "UUU", "topicName": "UUU"},


    {"name": "VVV", "topicName": "VVV"},


    {"name": "Wordplay", "topicName": "Wordplay"},
    {"name": "Women & Men", "topicName": "WomenAndMen"},
    {"name": "Women vs. Men", "topicName": "WomenVsMen"},


    {"name": "YYY", "topicName": "YYY"},
    

    {"name": "ZZZ", "topicName": "ZZZ"}

]